odoo/addons/purchase_order_qty_change_no_recompute/README.rst
odoo/addons/purchase_order_qty_change_no_recompute/__init__.py
odoo/addons/purchase_order_qty_change_no_recompute/__manifest__.py
odoo/addons/purchase_order_qty_change_no_recompute/i18n/it.po
odoo/addons/purchase_order_qty_change_no_recompute/i18n/purchase_order_qty_change_no_recompute.pot
odoo/addons/purchase_order_qty_change_no_recompute/models/__init__.py
odoo/addons/purchase_order_qty_change_no_recompute/models/purchase_order.py
odoo/addons/purchase_order_qty_change_no_recompute/readme/CONTRIBUTORS.rst
odoo/addons/purchase_order_qty_change_no_recompute/readme/DESCRIPTION.rst
odoo/addons/purchase_order_qty_change_no_recompute/readme/USAGE.rst
odoo/addons/purchase_order_qty_change_no_recompute/static/description/icon.png
odoo/addons/purchase_order_qty_change_no_recompute/static/description/index.html
odoo/addons/purchase_order_qty_change_no_recompute/tests/__init__.py
odoo/addons/purchase_order_qty_change_no_recompute/tests/test_purchase_order_qty_change.py
odoo14_addon_purchase_order_qty_change_no_recompute-14.0.1.0.1.dev6.dist-info/METADATA
odoo14_addon_purchase_order_qty_change_no_recompute-14.0.1.0.1.dev6.dist-info/WHEEL
odoo14_addon_purchase_order_qty_change_no_recompute-14.0.1.0.1.dev6.dist-info/top_level.txt
odoo14_addon_purchase_order_qty_change_no_recompute-14.0.1.0.1.dev6.dist-info/RECORD
